{
  "kind": "collectionType",
  "collectionName": "invoices",
  "info": {
    "singularName": "invoice",
    "pluralName": "invoices",
    "displayName": "invoice",
    "description": ""
  },
  "options": {
    "draftAndPublish": true
  },
  "pluginOptions": {},
  "attributes": {
    "phoneNumber": {
      "type": "string",
      "required": true,
      "unique": true
    },
    "fullName": {
      "type": "string",
      "required": true
    },
    "email": {
      "type": "string"
    },
    "datetime": {
      "type": "datetime"
    },
    "address": {
      "type": "text"
    },
    "orderId": {
      "type": "string"
    },
    "uA": {
      "type": "string"
    },
    "overTotal": {
      "type": "float"
    },
    "orderCode": {
      "type": "string"
    },
    "city": {
      "type": "string"
    }
  }
}
